Metadata-Version: 2.1
Name: ast_scope
Version: 0.5.2
Summary: Annotates a Python AST with the scope of symbols.
Home-page: https://github.com/kavigupta/ast_scope
Author: Kavi Gupta
Author-email: ast_scope@kavigupta.org
Classifier: Programming Language :: Python :: 3.9
Classifier: Programming Language :: Python :: 3.10
Classifier: Programming Language :: Python :: 3.11
Classifier: Programming Language :: Python :: 3.12
Classifier: Programming Language :: Python :: 3.13
Classifier: Operating System :: OS Independent
Requires-Python: >=3.9
License-File: LICENSE
Requires-Dist: attrs>=19.3.0
Requires-Dist: typing-extensions>=4.13.2
